README.md
setup.py
pyjboss/__init__.py
pyjboss/__main__.py
pyjboss/transport.py
pyjboss.egg-info/PKG-INFO
pyjboss.egg-info/SOURCES.txt
pyjboss.egg-info/dependency_links.txt
pyjboss.egg-info/requires.txt
pyjboss.egg-info/top_level.txt
pyjboss/client/__init__.py
pyjboss/client/datasource.py
pyjboss/client/deployment.py
pyjboss/client/ejb.py
pyjboss/client/logging.py
pyjboss/client/message.py
pyjboss/client/namespacedclient.py
pyjboss/client/utils.py